history/__init__.py
history/admin.py
history/backends/__init__.py
history/backends/base.py
history/backends/postgres.py
history/backends/sqlite.py
history/contrib/__init__.py
history/contrib/loaddata/__init__.py
history/contrib/loaddata/apps.py
history/contrib/loaddata/management/__init__.py
history/contrib/loaddata/management/commands/__init__.py
history/contrib/loaddata/management/commands/loaddata.py
history/contrib/migrate/__init__.py
history/contrib/migrate/apps.py
history/contrib/migrate/management/__init__.py
history/contrib/migrate/management/commands/__init__.py
history/contrib/migrate/management/commands/migrate.py
history/management/__init__.py
history/management/commands/__init__.py
history/management/commands/triggers.py
history/middleware.py
history/migrations/0001_initial.py
history/migrations/__init__.py
history/models.py
history/templates/history/admin_history.html
history/templatetags/__init__.py
history/templatetags/history.py
history/utils.py
django_history_triggers-3.6.0.dist-info/WHEEL
django_history_triggers-3.6.0.dist-info/METADATA
django_history_triggers-3.6.0.dist-info/RECORD
