Metadata-Version: 2.3
Name: django-history-triggers
Version: 3.6.0
Summary: Management command and middleware for Django history triggers.
Author: Dan Watson
Author-email: Dan Watson <watsond@imsweb.com>
License: BSD-2-Clause
Classifier: Development Status :: 5 - Production/Stable
Classifier: Intended Audience :: Developers
Classifier: License :: OSI Approved :: BSD License
Classifier: Operating System :: OS Independent
Classifier: Programming Language :: Python
Classifier: Programming Language :: Python :: 3
Classifier: Topic :: Utilities
Requires-Python: >=3.10
Project-URL: Repository, https://github.com/imsweb/django-history-triggers
